elcebo/__init__.py
elcebo/client.py
elcebo/endpoint.py
elcebo/exceptions.py
elcebo/endpoints/__init__.py
elcebo/endpoints/data_view.py
elcebo/endpoints/data_view2.py
elcebo/endpoints/ilm.py
elcebo/endpoints/index_alias.py
elcebo/endpoints/kb_settings.py
elcebo/endpoints/role.py
elcebo/endpoints/role_mapping.py
elcebo/endpoints/snapshot.py
elcebo/endpoints/space.py
elcebo/templates/data_view/base.json.j2
elcebo/templates/data_view/base2.json.j2
elcebo/templates/index_alias/subscription_filter.json.j2
elcebo/templates/role/cross_cluster_local.json.j2
elcebo/templates/role/cross_cluster_remote.json.j2
elcebo/templates/role/kibana_advanced.json.j2
elcebo/templates/role/kibana_base.json.j2
elcebo/templates/role/synthetics_setup.json.j2
elcebo/templates/role/synthetics_writer.json.j2
elcebo/templates/role_mapping/oidc.json.j2
elcebo-0.0.3.dist-info/METADATA
elcebo-0.0.3.dist-info/WHEEL
elcebo-0.0.3.dist-info/licenses/LICENSE
elcebo-0.0.3.dist-info/RECORD
